bb7-0.5.5.dist-info/METADATA
bb7-0.5.5.dist-info/WHEEL
bb7-0.5.5.dist-info/entry_points.txt
bb7-0.5.5.dist-info/licenses/LICENSE
bb7/__init__.py
bb7/chat.py
bb7/cli.py
bb7/examine.py
bb7/rag.py
bb7/utils.py
bb7/write.py
bb7-0.5.5.dist-info/RECORD
