Metadata-Version: 2.1
Name: bb7
Version: 0.5.5
Summary: A TDD coding bot
Author-Email: Drunkwcodes <drunkwcodes@gmail.com>
License: MIT
Project-URL: Homepage, https://github.com/drunkwcodes/bb7
Project-URL: Issues, https://github.com/drunkwcodes/bb7/issues
Requires-Python: >=3.11
Requires-Dist: rich>=13.7.1
Requires-Dist: ollama>=0.3.1
Requires-Dist: click>=8.1.7
Requires-Dist: pytest>=8.3.2
Requires-Dist: gTTS>=2.5.3
Requires-Dist: pygame>=2.6.0
Requires-Dist: prompt-toolkit>=3.0.47
Requires-Dist: platformdirs>=4.3.1
Requires-Dist: pytest-cov>=5.0.0
Requires-Dist: tomlkit>=0.13.2
Requires-Dist: llama-index>=0.11.14
Requires-Dist: llama-index-embeddings-huggingface>=0.3.1
Requires-Dist: llama-index-readers-file>=0.2.2
Requires-Dist: chromadb>=0.5.11
Requires-Dist: llama-index-vector-stores-chroma>=0.2.0
Requires-Dist: llama-index-llms-ollama>=0.3.3
Requires-Dist: peewee>=3.17.6
